{
    "title": "change的技术驿站",
    "author": "vonchange",
    "baidu-site-verification":"cAxqlT3C5k",
    "description": "change技术驿站",
    "language": "zh-hans",
    "gitbook": "3.2.3",
    "links": {
        "sidebar": {
            "change的技术博客": "http://www.vonchange.com/"
        }
    },
    "plugins": [
        "toc",
        "theme-comscore",
        "3-ba",
        "-lunr",
        "-search",
        "search-plus",
        "splitter",
        "-sharing",
        "sharing-plus",
        "expandable-chapters-small",
        "anchor-navigation-ex",
        "edit-link-plus",
        "code",
        "chart",
        "favicon-absolute",
        "github-buttons",
        "advanced-emoji",
        "rss",
        "sitemap-general",
        "copyright",
        "tbfed-pagefooter",
        "mygitalk",
        "donate",
        "diff",
        "simple-mind-map",
        "hide-element",
        "audio_image",
        "icp",
        "mermaid-gb3"
    ],
    "pluginsConfig": {
        "favicon-absolute": {
            "favicon": "/favicon.ico",
            "appleTouchIconPrecomposed152": "/apple-touch-icon-precomposed-152.png"
        },
        "toc": {
            "addClass": true,
            "className": "toc"
        },
        "github-buttons": {
            "buttons": [{
                "user": "vonchange",
                "repo": "vonchange.github.io",
                "type": "star",
                "size": "small"
            }]
        },
        "icp": {
            "number": "鲁ICP备20022988号"
        },
        "3-ba": {
            "token": "07ec7e1b1f91c8a8828cb7504bf53222"
        },
        "sharing": {
            "douban": true,
            "facebook": false,
            "google": false,
            "hatenaBookmark": false,
            "instapaper": false,
            "line": false,
            "linkedin": false,
            "messenger": false,
            "pocket": false,
            "qq": true,
            "qzone": true,
            "stumbleupon": false,
            "twitter": false,
            "viber": false,
            "vk": false,
            "weibo": true,
            "whatsapp": false,
            "all": [
                "facebook", "google", "twitter",
                "weibo", "instapaper", "linkedin",
                "pocket", "stumbleupon"
            ]
        },
        "edit-link-plus": {
            "base": {
              "vonchange.github.io":"https://github.com/VonChange/VonChange.github.io/edit/master"
            },
            "defaultBase": "https://github.com/VonChange/VonChange.github.io/edit/master",
            "label": "编辑本页"
        },
        "chart": {
            "type": "c3"
        },
        "rss": {
            "title": "change技术驿站",
            "description": "change技术驿站",
            "author": "vonchange",
            "site_url": "http://www.vonchange.com/",
            "feed_url": "http://www.vonchange.com/rss",
            "managingEditor": "vonchange@163.com",
            "webMaster": "vonchange@163.com",
            "categories": [
                "orm",
                "k8s",
                "devops",
                "java"
            ]
        },
        "sitemap-general": {
            "prefix": "http://www.vonchange.com/"
        },
        "copyright": {
            "site": "http://www.vonchange.com/",
            "author": "change",
            "website": "change的技术驿站",
            "copyProtect": false
        },
        "tbfed-pagefooter": {
            "copyright": "&copy vonchange",
            "modify_label": "文件修订时间: ",
            "modify_format": "YYYY-MM-DD HH:mm:ss"
        },
        "mygitalk": {
            "clientID": "7f7363b6e6e3c9a06f4f",
            "clientSecret": "6e71673a0cfb622b535af4c00b0622cf2d34d31b",
            "repo": "vonchange.github.io",
            "owner": "vonchange",
            "admin": ["vonchange"],
            "distractionFreeMode": false
        },
        "donate": {
            "wechat": "/doc/image/wx.jpeg",
            "alipay": "/doc/image/zfb.jpeg",
            "title": "",
            "button": "赏",
            "alipayText": "支付宝",
            "wechatText": "微信"
        },
        "hide-element": {
            "elements": ["a.gitbook-link[href='https://www.gitbook.com']"]
        },
        "simple-mind-map":{
            "preset": "colorful"
        }
    }
}
